{"dataset_id": 42, "name": "soybean", "version": 1, "description": "**Author**: R.S. Michalski and R.L. Chilausky (Donors: Ming Tan & Jeff Schlimmer)  \n**Source**: [UCI](https://archive.ics.uci.edu/ml/datasets/Soybean+(Large)) - 1988  \n**Please cite**: R.S. Michalski and R.L. Chilausky \"Learning by Being Told and Learning from Examples: An Experimental Comparison of the Two Methods of Knowledge Acquisition in the Context of Developing an Expert System for Soybean Disease Diagnosis\", International Journal of Policy Analysis and Information Systems, Vol. 4, No. 2, 1980.  \n\n**Large Soybean Database**  \nThis is the large soybean database from the UCI repository, with its training and test database combined into a single file. \n\nThere are 19 classes, only the first 15 of which have been used in prior work. The folklore seems to be that the last four classes are unjustified by the data since they have so few examples. There are 35 categorical attributes, some nominal and some ordered. The value 'dna' means does not apply. The values for attributes are encoded numerically, with the first value encoded as \"0,'' the second as \"1,'' and so forth. An unknown value is encoded as \"?''.\n\n### Attribute Information\n\n1. date: april,may,june,july,august,september,october,?. \n2. plant-stand: normal,lt-normal,?. \n3. precip: lt-norm,norm,gt-norm,?. \n4. temp: lt-norm,norm,gt-norm,?. \n5. hail: yes,no,?. \n6. crop-hist: diff-lst-year,same-lst-yr,same-lst-two-yrs, \nsame-lst-sev-yrs,?. \n7. area-damaged: scattered,low-areas,upper-areas,whole-field,?. \n8. severity: minor,pot-severe,severe,?. \n9. seed-tmt: none,fungicide,other,?. \n10. germination: 90-100%,80-89%,lt-80%,?. \n11. plant-growth: norm,abnorm,?. \n12. leaves: norm,abnorm. \n13. leafspots-halo: absent,yellow-halos,no-yellow-halos,?. \n14. leafspots-marg: w-s-marg,no-w-s-marg,dna,?. \n15. leafspot-size: lt-1/8,gt-1/8,dna,?. \n16. leaf-shread: absent,present,?. \n17. leaf-malf: absent,present,?. \n18. leaf-mild: absent,upper-surf,lower-surf,?. \n19. stem: norm,abnorm,?. \n20. lodging: yes,no,?. \n21. stem-cankers: absent,below-soil,above-soil,above-sec-nde,?. \n22. canker-lesion: dna,brown,dk-brown-blk,tan,?. \n23. fruiting-bodies: absent,present,?. \n24. external decay: absent,firm-and-dry,watery,?. \n25. mycelium: absent,present,?. \n26. int-discolor: none,brown,black,?. \n27. sclerotia: absent,present,?. \n28. fruit-pods: norm,diseased,few-present,dna,?. \n29. fruit spots: absent,colored,brown-w/blk-specks,distort,dna,?. \n30. seed: norm,abnorm,?. \n31. mold-growth: absent,present,?. \n32. seed-discolor: absent,present,?. \n33. seed-size: norm,lt-norm,?. \n34. shriveling: absent,present,?. \n35. roots: norm,rotted,galls-cysts,?.\n\n### Classes \n\n-- 19 Classes = {diaporthe-stem-canker, charcoal-rot, rhizoctonia-root-rot, phytophthora-rot, brown-stem-rot, powdery-mildew, downy-mildew, brown-spot, bacterial-blight, bacterial-pustule, purple-seed-stain, anthracnose, phyllosticta-leaf-spot, alternarialeaf-spot, frog-eye-leaf-spot, diaporthe-pod-&-stem-blight, cyst-nematode, 2-4-d-injury, herbicide-injury} \n\n### Revelant papers\n\nTan, M., & Eshelman, L. (1988). Using weighted networks to represent classification knowledge in noisy domains. Proceedings of the Fifth International Conference on Machine Learning (pp. 121-134). Ann Arbor, Michigan: Morgan Kaufmann. \n\nFisher,D.H. & Schlimmer,J.C. (1988). Concept Simplification and Predictive Accuracy. Proceedings of the Fifth International Conference on Machine Learning (pp. 22-28). Ann Arbor, Michigan: Morgan Kaufmann.", "creator": ["R.S. Michalski", "R.L. Chilausky"], "contributor": null, "collection_date": "1988-07-11", "upload_date": "2014-04-06T23:22:32", "language": "English", "license": "Public", "default_target_attribute": "class", "row_id_attribute": null, "ignore_attribute": null, "tags": ["OpenML100", "study_1", "study_123", "study_135", "study_14", "study_34", "study_37", "study_41", "study_70", "study_76", "uci"], "features": [{"index": 0, "name": "date", "data_type": "nominal", "nominal_values": ["april", "august", "july", "june", "may", "october", "september"], "number_missing_values": 1}, {"index": 1, "name": "plant-stand", "data_type": "nominal", "nominal_values": ["lt-normal", "normal"], "number_missing_values": 36}, {"index": 2, "name": "precip", "data_type": "nominal", "nominal_values": ["gt-norm", "lt-norm", "norm"], "number_missing_values": 38}, {"index": 3, "name": "temp", "data_type": "nominal", "nominal_values": ["gt-norm", "lt-norm", "norm"], "number_missing_values": 30}, {"index": 4, "name": "hail", "data_type": "nominal", "nominal_values": ["no", "yes"], "number_missing_values": 121}, {"index": 5, "name": "crop-hist", "data_type": "nominal", "nominal_values": ["diff-lst-year", "same-lst-sev-yrs", "same-lst-two-yrs", "same-lst-yr"], "number_missing_values": 16}, {"index": 6, "name": "area-damaged", "data_type": "nominal", "nominal_values": ["low-areas", "scattered", "upper-areas", "whole-field"], "number_missing_values": 1}, {"index": 7, "name": "severity", "data_type": "nominal", "nominal_values": ["minor", "pot-severe", "severe"], "number_missing_values": 121}, {"index": 8, "name": "seed-tmt", "data_type": "nominal", "nominal_values": ["fungicide", "none", "other"], "number_missing_values": 121}, {"index": 9, "name": "germination", "data_type": "nominal", "nominal_values": ["80-89", "90-100", "lt-80"], "number_missing_values": 112}, {"index": 10, "name": "plant-growth", "data_type": "nominal", "nominal_values": ["abnorm", "norm"], "number_missing_values": 16}, {"index": 11, "name": "leaves", "data_type": "nominal", "nominal_values": ["abnorm", "norm"], "number_missing_values": 0}, {"index": 12, "name": "leafspots-halo", "data_type": "nominal", "nominal_values": ["absent", "no-yellow-halos", "yellow-halos"], "number_missing_values": 84}, {"index": 13, "name": "leafspots-marg", "data_type": "nominal", "nominal_values": ["dna", "no-w-s-marg", "w-s-marg"], "number_missing_values": 84}, {"index": 14, "name": "leafspot-size", "data_type": "nominal", "nominal_values": ["dna", "gt-1/8", "lt-1/8"], "number_missing_values": 84}, {"index": 15, "name": "leaf-shread", "data_type": "nominal", "nominal_values": ["absent", "present"], "number_missing_values": 100}, {"index": 16, "name": "leaf-malf", "data_type": "nominal", "nominal_values": ["absent", "present"], "number_missing_values": 84}, {"index": 17, "name": "leaf-mild", "data_type": "nominal", "nominal_values": ["absent", "lower-surf", "upper-surf"], "number_missing_values": 108}, {"index": 18, "name": "stem", "data_type": "nominal", "nominal_values": ["abnorm", "norm"], "number_missing_values": 16}, {"index": 19, "name": "lodging", "data_type": "nominal", "nominal_values": ["no", "yes"], "number_missing_values": 121}, {"index": 20, "name": "stem-cankers", "data_type": "nominal", "nominal_values": ["above-sec-nde", "above-soil", "absent", "below-soil"], "number_missing_values": 38}, {"index": 21, "name": "canker-lesion", "data_type": "nominal", "nominal_values": ["brown", "dk-brown-blk", "dna", "tan"], "number_missing_values": 38}, {"index": 22, "name": "fruiting-bodies", "data_type": "nominal", "nominal_values": ["absent", "present"], "number_missing_values": 106}, {"index": 23, "name": "external-decay", "data_type": "nominal", "nominal_values": ["absent", "firm-and-dry", "watery"], "number_missing_values": 38}, {"index": 24, "name": "mycelium", "data_type": "nominal", "nominal_values": ["absent", "present"], "number_missing_values": 38}, {"index": 25, "name": "int-discolor", "data_type": "nominal", "nominal_values": ["black", "brown", "none"], "number_missing_values": 38}, {"index": 26, "name": "sclerotia", "data_type": "nominal", "nominal_values": ["absent", "present"], "number_missing_values": 38}, {"index": 27, "name": "fruit-pods", "data_type": "nominal", "nominal_values": ["diseased", "dna", "few-present", "norm"], "number_missing_values": 84}, {"index": 28, "name": "fruit-spots", "data_type": "nominal", "nominal_values": ["absent", "brown-w/blk-specks", "colored", "distort", "dna"], "number_missing_values": 106}, {"index": 29, "name": "seed", "data_type": "nominal", "nominal_values": ["abnorm", "norm"], "number_missing_values": 92}, {"index": 30, "name": "mold-growth", "data_type": "nominal", "nominal_values": ["absent", "present"], "number_missing_values": 92}, {"index": 31, "name": "seed-discolor", "data_type": "nominal", "nominal_values": ["absent", "present"], "number_missing_values": 106}, {"index": 32, "name": "seed-size", "data_type": "nominal", "nominal_values": ["lt-norm", "norm"], "number_missing_values": 92}, {"index": 33, "name": "shriveling", "data_type": "nominal", "nominal_values": ["absent", "present"], "number_missing_values": 106}, {"index": 34, "name": "roots", "data_type": "nominal", "nominal_values": ["galls-cysts", "norm", "rotted"], "number_missing_values": 31}, {"index": 35, "name": "class", "data_type": "nominal", "nominal_values": ["2-4-d-injury", "alternarialeaf-spot", "anthracnose", "bacterial-blight", "bacterial-pustule", "brown-spot", "brown-stem-rot", "charcoal-rot", "cyst-nematode", "diaporthe-pod-&-stem-blight", "diaporthe-stem-canker", "downy-mildew", "frog-eye-leaf-spot", "herbicide-injury", "phyllosticta-leaf-spot", "phytophthora-rot", "powdery-mildew", "purple-seed-stain", "rhizoctonia-root-rot"], "number_missing_values": 0}], "qualities": {"AutoCorrelation": 0.9457478005865103, "CfsSubsetEval_DecisionStumpAUC": 0.9620422408823379, "CfsSubsetEval_DecisionStumpErrRate": 0.13323572474377746, "CfsSubsetEval_DecisionStumpKappa": 0.8534752853145238, "CfsSubsetEval_NaiveBayesAUC": 0.9620422408823379, "CfsSubsetEval_NaiveBayesErrRate": 0.13323572474377746, "CfsSubsetEval_NaiveBayesKappa": 0.8534752853145238, "CfsSubsetEval_kNN1NAUC": 0.9620422408823379, "CfsSubsetEval_kNN1NErrRate": 0.13323572474377746, "CfsSubsetEval_kNN1NKappa": 0.8534752853145238, "ClassEntropy": 3.83550798457672, "DecisionStumpAUC": 0.8099631489104341, "DecisionStumpErrRate": 0.7203513909224012, "DecisionStumpKappa": 0.19424522533539545, "Dimensionality": 0.0527086383601757, "EquivalentNumberOfAtts": 7.508591767241043, "J48.00001.AUC": 0.9739047068470593, "J48.00001.ErrRate": 0.12152269399707175, "J48.00001.Kappa": 0.8663370421980624, "J48.0001.AUC": 0.9739047068470593, "J48.0001.ErrRate": 0.12152269399707175, "J48.0001.Kappa": 0.8663370421980624, "J48.001.AUC": 0.9739047068470593, "J48.001.ErrRate": 0.12152269399707175, "J48.001.Kappa": 0.8663370421980624, "MajorityClassPercentage": 13.469985358711567, "MajorityClassSize": 92.0, "MaxAttributeEntropy": 2.6849389644492594, "MaxKurtosisOfNumericAtts": NaN, "MaxMeansOfNumericAtts": NaN, "MaxMutualInformation": 1.28692474762189, "MaxNominalAttDistinctValues": 19.0, "MaxSkewnessOfNumericAtts": NaN, "MaxStdDevOfNumericAtts": NaN, "MeanAttributeEntropy": 0.9655890619117928, "MeanKurtosisOfNumericAtts": NaN, "MeanMeansOfNumericAtts": NaN, "MeanMutualInformation": 0.5108158897798274, "MeanNoiseToSignalRatio": 0.8902878340922058, "MeanNominalAttDistinctValues": 3.2777777777777777, "MeanSkewnessOfNumericAtts": NaN, "MeanStdDevOfNumericAtts": NaN, "MinAttributeEntropy": 0.07262476248540556, "MinKurtosisOfNumericAtts": NaN, "MinMeansOfNumericAtts": NaN, "MinMutualInformation": 0.0468182939867, "MinNominalAttDistinctValues": 2.0, "MinSkewnessOfNumericAtts": NaN, "MinStdDevOfNumericAtts": NaN, "MinorityClassPercentage": 1.171303074670571, "MinorityClassSize": 8.0, "NaiveBayesAUC": 0.9921587580230303, "NaiveBayesErrRate": 0.08931185944363104, "NaiveBayesKappa": 0.9019654903843212, "NumberOfBinaryFeatures": 16.0, "NumberOfClasses": 19.0, "NumberOfFeatures": 36.0, "NumberOfInstances": 683.0, "NumberOfInstancesWithMissingValues": 121.0, "NumberOfMissingValues": 2337.0, "NumberOfNumericFeatures": 0.0, "NumberOfSymbolicFeatures": 36.0, "PercentageOfBinaryFeatures": 44.44444444444444, "PercentageOfInstancesWithMissingValues": 17.71595900439239, "PercentageOfMissingValues": 9.504636408003904, "PercentageOfNumericFeatures": 0.0, "PercentageOfSymbolicFeatures": 100.0, "Quartile1AttributeEntropy": 0.4629328593168401, "Quartile1KurtosisOfNumericAtts": NaN, "Quartile1MeansOfNumericAtts": NaN, "Quartile1MutualInformation": 0.26369905545327, "Quartile1SkewnessOfNumericAtts": NaN, "Quartile1StdDevOfNumericAtts": NaN, "Quartile2AttributeEntropy": 0.9158362664344971, "Quartile2KurtosisOfNumericAtts": NaN, "Quartile2MeansOfNumericAtts": NaN, "Quartile2MutualInformation": 0.45996721558355, "Quartile2SkewnessOfNumericAtts": NaN, "Quartile2StdDevOfNumericAtts": NaN, "Quartile3AttributeEntropy": 1.408326420019514, "Quartile3KurtosisOfNumericAtts": NaN, "Quartile3MeansOfNumericAtts": NaN, "Quartile3MutualInformation": 0.71879499353135, "Quartile3SkewnessOfNumericAtts": NaN, "Quartile3StdDevOfNumericAtts": NaN, "REPTreeDepth1AUC": 0.9436075624852911, "REPTreeDepth1ErrRate": 0.26500732064421667, "REPTreeDepth1Kappa": 0.7052208643815201, "REPTreeDepth2AUC": 0.9436075624852911, "REPTreeDepth2ErrRate": 0.26500732064421667, "REPTreeDepth2Kappa": 0.7052208643815201, "REPTreeDepth3AUC": 0.9436075624852911, "REPTreeDepth3ErrRate": 0.26500732064421667, "REPTreeDepth3Kappa": 0.7052208643815201, "RandomTreeDepth1AUC": 0.9035959879652148, "RandomTreeDepth1ErrRate": 0.18594436310395315, "RandomTreeDepth1Kappa": 0.7960191985250715, "RandomTreeDepth2AUC": 0.9035959879652148, "RandomTreeDepth2ErrRate": 0.18594436310395315, "RandomTreeDepth2Kappa": 0.7960191985250715, "RandomTreeDepth3AUC": 0.9035959879652148, "RandomTreeDepth3ErrRate": 0.18594436310395315, "RandomTreeDepth3Kappa": 0.7960191985250715, "StdvNominalAttDistinctValues": 2.884551077834282, "kNN1NAUC": 0.9616161058225481, "kNN1NErrRate": 0.1171303074670571, "kNN1NKappa": 0.871344781387376}}