{"dataset_id": 42911, "name": "risk-factors-cervical", "version": 1, "description": "**Author**: Kelwin Fernandes, Jaime S. Cardoso, Jessica Fernandes\n**Source**: [UCI](https://archive.ics.uci.edu/ml/datasets/Cervical+cancer+%28Risk+Factors%29) - 2017\n**Please cite**: [Paper](https://link.springer.com/chapter/10.1007/978-3-319-58838-4_27)  \n\n**Cervical cancer (Risk Factors) Data Set**\n\nThe dataset was collected at 'Hospital Universitario de Caracas' in Caracas, Venezuela. The dataset comprises demographic information, habits, and historic medical records of 858 patients. Several patients decided not to answer some of the questions because of privacy concerns (missing values).\n\n### Attribute information\n\n- (int) Age \n- (int) Number of sexual partners \n- (int) First sexual intercourse (age) \n- (int) Num of pregnancies \n- (bool) Smokes \n- (bool) Smokes (years) \n- (bool) Smokes (packs/year) \n- (bool) Hormonal Contraceptives \n- (int) Hormonal Contraceptives (years) \n- (bool) IUD \n- (int) IUD (years) \n- (bool) STDs \n- (int) STDs (number) \n- (bool) STDs:condylomatosis \n- (bool) STDs:cervical condylomatosis \n- (bool) STDs:vaginal condylomatosis \n- (bool) STDs:vulvo-perineal condylomatosis \n- (bool) STDs:syphilis \n- (bool) STDs:pelvic inflammatory disease \n- (bool) STDs:genital herpes \n- (bool) STDs:molluscum contagiosum \n- (bool) STDs:AIDS \n- (bool) STDs:HIV \n- (bool) STDs:Hepatitis B \n- (bool) STDs:HPV \n- (int) STDs: Number of diagnosis \n- (int) STDs: Time since first diagnosis \n- (int) STDs: Time since last diagnosis \n- (bool) Dx:Cancer \n- (bool) Dx:CIN \n- (bool) Dx:HPV \n- (bool) Dx \n- (bool) Hinselmann: target variable \n- (bool) Schiller: target variable \n- (bool) Cytology: target variable \n- (bool) Biopsy: target variable", "creator": ["Kelwin Fernandes", "Jaime S. Cardoso", "Jessica Fernandes"], "contributor": null, "collection_date": "03-03-2017", "upload_date": "2021-05-19T21:39:50", "language": "English", "license": "CC-BY", "default_target_attribute": null, "row_id_attribute": null, "ignore_attribute": null, "tags": null, "features": [{"index": 0, "name": "Age", "data_type": "numeric", "nominal_values": null, "number_missing_values": 0}, {"index": 1, "name": "Number of sexual partners", "data_type": "string", "nominal_values": null, "number_missing_values": 26}, {"index": 2, "name": "First sexual intercourse", "data_type": "string", "nominal_values": null, "number_missing_values": 7}, {"index": 3, "name": "Num of pregnancies", "data_type": "string", "nominal_values": null, "number_missing_values": 56}, {"index": 4, "name": "Smokes", "data_type": "string", "nominal_values": null, "number_missing_values": 13}, {"index": 5, "name": "Smokes (years)", "data_type": "string", "nominal_values": null, "number_missing_values": 13}, {"index": 6, "name": "Smokes (packs/year)", "data_type": "string", "nominal_values": null, "number_missing_values": 13}, {"index": 7, "name": "Hormonal Contraceptives", "data_type": "string", "nominal_values": null, "number_missing_values": 108}, {"index": 8, "name": "Hormonal Contraceptives (years)", "data_type": "string", "nominal_values": null, "number_missing_values": 108}, {"index": 9, "name": "IUD", "data_type": "string", "nominal_values": null, "number_missing_values": 117}, {"index": 10, "name": "IUD (years)", "data_type": "string", "nominal_values": null, "number_missing_values": 117}, {"index": 11, "name": "STDs", "data_type": "string", "nominal_values": null, "number_missing_values": 105}, {"index": 12, "name": "STDs (number)", "data_type": "string", "nominal_values": null, "number_missing_values": 105}, {"index": 13, "name": "STDs:condylomatosis", "data_type": "string", "nominal_values": null, "number_missing_values": 105}, {"index": 14, "name": "STDs:cervical condylomatosis", "data_type": "string", "nominal_values": null, "number_missing_values": 105}, {"index": 15, "name": "STDs:vaginal condylomatosis", "data_type": "string", "nominal_values": null, "number_missing_values": 105}, {"index": 16, "name": "STDs:vulvo-perineal condylomatosis", "data_type": "string", "nominal_values": null, "number_missing_values": 105}, {"index": 17, "name": "STDs:syphilis", "data_type": "string", "nominal_values": null, "number_missing_values": 105}, {"index": 18, "name": "STDs:pelvic inflammatory disease", "data_type": "string", "nominal_values": null, "number_missing_values": 105}, {"index": 19, "name": "STDs:genital herpes", "data_type": "string", "nominal_values": null, "number_missing_values": 105}, {"index": 20, "name": "STDs:molluscum contagiosum", "data_type": "string", "nominal_values": null, "number_missing_values": 105}, {"index": 21, "name": "STDs:AIDS", "data_type": "string", "nominal_values": null, "number_missing_values": 105}, {"index": 22, "name": "STDs:HIV", "data_type": "string", "nominal_values": null, "number_missing_values": 105}, {"index": 23, "name": "STDs:Hepatitis B", "data_type": "string", "nominal_values": null, "number_missing_values": 105}, {"index": 24, "name": "STDs:HPV", "data_type": "string", "nominal_values": null, "number_missing_values": 105}, {"index": 25, "name": "STDs: Number of diagnosis", "data_type": "numeric", "nominal_values": null, "number_missing_values": 0}, {"index": 26, "name": "STDs: Time since first diagnosis", "data_type": "string", "nominal_values": null, "number_missing_values": 787}, {"index": 27, "name": "STDs: Time since last diagnosis", "data_type": "string", "nominal_values": null, "number_missing_values": 787}, {"index": 28, "name": "Dx:Cancer", "data_type": "numeric", "nominal_values": null, "number_missing_values": 0}, {"index": 29, "name": "Dx:CIN", "data_type": "numeric", "nominal_values": null, "number_missing_values": 0}, {"index": 30, "name": "Dx:HPV", "data_type": "numeric", "nominal_values": null, "number_missing_values": 0}, {"index": 31, "name": "Dx", "data_type": "numeric", "nominal_values": null, "number_missing_values": 0}, {"index": 32, "name": "Hinselmann", "data_type": "numeric", "nominal_values": null, "number_missing_values": 0}, {"index": 33, "name": "Schiller", "data_type": "numeric", "nominal_values": null, "number_missing_values": 0}, {"index": 34, "name": "Citology", "data_type": "numeric", "nominal_values": null, "number_missing_values": 0}, {"index": 35, "name": "Biopsy", "data_type": "numeric", "nominal_values": null, "number_missing_values": 0}], "qualities": {"AutoCorrelation": NaN, "Dimensionality": 0.04195804195804196, "MajorityClassPercentage": NaN, "MajorityClassSize": NaN, "MinorityClassPercentage": NaN, "MinorityClassSize": NaN, "NumberOfBinaryFeatures": 0.0, "NumberOfClasses": NaN, "NumberOfFeatures": 36.0, "NumberOfInstances": 858.0, "NumberOfInstancesWithMissingValues": 799.0, "NumberOfMissingValues": 3622.0, "NumberOfNumericFeatures": 10.0, "NumberOfSymbolicFeatures": 0.0, "PercentageOfBinaryFeatures": 0.0, "PercentageOfInstancesWithMissingValues": 93.12354312354313, "PercentageOfMissingValues": 11.726236726236726, "PercentageOfNumericFeatures": 27.77777777777778, "PercentageOfSymbolicFeatures": 0.0}}