{"dataset_id": 43437, "name": "Gender-Recognition-by-Voice", "version": 1, "description": "Voice Gender\nGender Recognition by Voice and Speech Analysis\nThis database was created to identify a voice as male or female, based upon acoustic properties of the voice and speech. The dataset consists of 3,168 recorded voice samples, collected from male and female speakers. The voice samples are pre-processed by acoustic analysis in R using the seewave and tuneR packages, with an analyzed frequency range of 0hz-280hz (human vocal range).\nThe Dataset\nThe following acoustic properties of each voice are measured and included within the CSV:\n\nmeanfreq: mean frequency (in kHz)\nsd: standard deviation of frequency\nmedian: median frequency (in kHz)\nQ25: first quantile (in kHz)\nQ75: third quantile (in kHz)\nIQR: interquantile range (in kHz)\nskew: skewness (see note in specprop description)\nkurt: kurtosis (see note in specprop description)\nsp.ent: spectral entropy\nsfm: spectral flatness\nmode: mode frequency\ncentroid: frequency centroid (see specprop)\npeakf: peak frequency (frequency with highest energy)\nmeanfun: average of fundamental frequency measured across acoustic signal\nminfun: minimum fundamental frequency measured across acoustic signal\nmaxfun: maximum fundamental frequency measured across acoustic signal\nmeandom: average of dominant frequency measured across acoustic signal\nmindom: minimum of dominant frequency measured across acoustic signal\nmaxdom: maximum of dominant frequency measured across acoustic signal\ndfrange: range of dominant frequency measured across acoustic signal\nmodindx: modulation index. Calculated as the accumulated absolute difference between adjacent measurements of fundamental frequencies divided by the frequency range\nlabel: male or female\n\nAccuracy\nBaseline (always predict male)\n50 / 50\nLogistic Regression\n97 / 98\nCART\n96 / 97\nRandom Forest\n100 / 98\nSVM\n100 / 99\nXGBoost\n100 / 99\nResearch Questions\nAn original analysis of the data-set can be found in the following article: \nIdentifying the Gender of a Voice using Machine Learning\nThe best model achieves 99 accuracy on the test set. According to a CART model, it appears that looking at the mean fundamental frequency might be enough to accurately classify a voice. However, some male voices use a higher frequency, even though their resonance differs from female voices, and may be incorrectly classified as female. To the human ear, there is apparently more than simple frequency, that determines a voice's gender.\nQuestions\n\nWhat other features differ between male and female voices?\nCan we find a difference in resonance between male and female voices?\nCan we identify falsetto from regular voices? (separate data-set likely needed for this)\nAre there other interesting features in the data?\n\nCART Diagram\n\nMean fundamental frequency appears to be an indicator of voice gender, with a threshold of 140hz separating male from female classifications.\nReferences\nThe Harvard-Haskins Database of Regularly-Timed Speech\nTelecommunications  Signal Processing Laboratory (TSP) Speech Database at McGill University, Home\nVoxForge Speech Corpus, Home\nFestvox CMU_ARCTIC Speech Database at Carnegie Mellon University", "creator": null, "contributor": null, "collection_date": "26-08-2016", "upload_date": "2022-03-23T13:20:48", "language": "English", "license": "CC BY-NC-SA 4.0", "default_target_attribute": null, "row_id_attribute": null, "ignore_attribute": null, "tags": null, "features": [{"index": 0, "name": "meanfreq", "data_type": "numeric", "nominal_values": null, "number_missing_values": 0}, {"index": 1, "name": "sd", "data_type": "numeric", "nominal_values": null, "number_missing_values": 0}, {"index": 2, "name": "median", "data_type": "numeric", "nominal_values": null, "number_missing_values": 0}, {"index": 3, "name": "Q25", "data_type": "numeric", "nominal_values": null, "number_missing_values": 0}, {"index": 4, "name": "Q75", "data_type": "numeric", "nominal_values": null, "number_missing_values": 0}, {"index": 5, "name": "IQR", "data_type": "numeric", "nominal_values": null, "number_missing_values": 0}, {"index": 6, "name": "skew", "data_type": "numeric", "nominal_values": null, "number_missing_values": 0}, {"index": 7, "name": "kurt", "data_type": "numeric", "nominal_values": null, "number_missing_values": 0}, {"index": 8, "name": "sp.ent", "data_type": "numeric", "nominal_values": null, "number_missing_values": 0}, {"index": 9, "name": "sfm", "data_type": "numeric", "nominal_values": null, "number_missing_values": 0}, {"index": 10, "name": "mode", "data_type": "numeric", "nominal_values": null, "number_missing_values": 0}, {"index": 11, "name": "centroid", "data_type": "numeric", "nominal_values": null, "number_missing_values": 0}, {"index": 12, "name": "meanfun", "data_type": "numeric", "nominal_values": null, "number_missing_values": 0}, {"index": 13, "name": "minfun", "data_type": "numeric", "nominal_values": null, "number_missing_values": 0}, {"index": 14, "name": "maxfun", "data_type": "numeric", "nominal_values": null, "number_missing_values": 0}, {"index": 15, "name": "meandom", "data_type": "numeric", "nominal_values": null, "number_missing_values": 0}, {"index": 16, "name": "mindom", "data_type": "numeric", "nominal_values": null, "number_missing_values": 0}, {"index": 17, "name": "maxdom", "data_type": "numeric", "nominal_values": null, "number_missing_values": 0}, {"index": 18, "name": "dfrange", "data_type": "numeric", "nominal_values": null, "number_missing_values": 0}, {"index": 19, "name": "modindx", "data_type": "numeric", "nominal_values": null, "number_missing_values": 0}, {"index": 20, "name": "label", "data_type": "string", "nominal_values": null, "number_missing_values": 0}], "qualities": {"AutoCorrelation": NaN, "Dimensionality": 0.006628787878787879, "MajorityClassPercentage": NaN, "MajorityClassSize": NaN, "MinorityClassPercentage": NaN, "MinorityClassSize": NaN, "NumberOfBinaryFeatures": 0.0, "NumberOfClasses": NaN, "NumberOfFeatures": 21.0, "NumberOfInstances": 3168.0, "NumberOfInstancesWithMissingValues": 0.0, "NumberOfMissingValues": 0.0, "NumberOfNumericFeatures": 20.0, "NumberOfSymbolicFeatures": 0.0, "PercentageOfBinaryFeatures": 0.0, "PercentageOfInstancesWithMissingValues": 0.0, "PercentageOfMissingValues": 0.0, "PercentageOfNumericFeatures": 95.23809523809523, "PercentageOfSymbolicFeatures": 0.0}}