{"dataset_id": 44049, "name": "OnlineNewsPopularity", "version": 3, "description": "Dataset used in the tabular data benchmark https://github.com/LeoGrin/tabular-benchmark,  \n                                  transformed in the same way. This dataset belongs to the \"regression on categorical and\n                                  numerical features\" benchmark. Original description: \n \nVersion with url set as row id, creator data missing due to bad formatting.**Author**: Kelwin Fernandes (INESC TEC, Universidade doPorto), Pedro Vinagre (ALGORITMI Research Centre, Universidade do Minho), Paulo Cortez - ALGORITMI Research Centre (Universidade do Minho), Pedro Sernadela (Universidade de Aveiro)   \n\n**Source**: UCI  \n\n**Please cite**: K. Fernandes, P. Vinagre and P. Cortez. A Proactive Intelligent Decision Support System for Predicting the Popularity of Online News. Proceedings of the 17th EPIA 2015 - Portuguese Conference on Artificial Intelligence, September, Coimbra, Portugal.  \n\n\n\nThis dataset summarizes a heterogeneous set of features about articles published by Mashable in a period of two years. The goal is to predict the number of shares in social networks (popularity).\n\n\n\n* The articles were published by Mashable (www.mashable.com) and their content as the rights to reproduce it belongs to them. Hence, this dataset does not share the original content but some statistics associated with it. The original content be publicly accessed and retrieved using the provided urls. \n\n* Acquisition date: January 8, 2015 \n\n* The estimated relative performance values were estimated by the authors using a Random Forest classifier and a rolling windows as assessment method. See their article for more details on how the relative performance values were set.\n\n\n\n\n\nAttribute Information:\n\n\n\nNumber of Attributes: 61 (58 predictive attributes, 2 non-predictive, 1 goal field) \n\n\n\nAttribute Information: \n\n0. url: URL of the article (non-predictive) \n\n1. timedelta: Days between the article publication and the dataset acquisition (non-predictive) \n\n2. n_tokens_title: Number of words in the title \n\n3. n_tokens_content: Number of words in the content \n\n4. n_unique_tokens: Rate of unique words in the content \n\n5. n_non_stop_words: Rate of non-stop words in the content \n\n6. n_non_stop_unique_tokens: Rate of unique non-stop words in the content \n\n7. num_hrefs: Number of links \n\n8. num_self_hrefs: Number of links to other articles published by Mashable \n\n9. num_imgs: Number of images \n\n10. num_videos: Number of videos \n\n11. average_token_length: Average length of the words in the content \n\n12. num_keywords: Number of keywords in the metadata \n\n13. data_channel_is_lifestyle: Is data channel 'Lifestyle'? \n\n14. data_channel_is_entertainment: Is data channel 'Entertainment'? \n\n15. data_channel_is_bus: Is data channel 'Business'? \n\n16. data_channel_is_socmed: Is data channel 'Social Media'? \n\n17. data_channel_is_tech: Is data channel 'Tech'? \n\n18. data_channel_is_world: Is data channel 'World'? \n\n19. kw_min_min: Worst keyword (min. shares) \n\n20. kw_max_min: Worst keyword (max. shares) \n\n21. kw_avg_min: Worst keyword (avg. shares) \n\n22. kw_min_max: Best keyword (min. shares) \n\n23. kw_max_max: Best keyword (max. shares) \n\n24. kw_avg_max: Best keyword (avg. shares) \n\n25. kw_min_avg: Avg. keyword (min. shares) \n\n26. kw_max_avg: Avg. keyword (max. shares) \n\n27. kw_avg_avg: Avg. keyword (avg. shares) \n\n28. self_reference_min_shares: Min. shares of referenced articles in Mashable \n\n29. self_reference_max_shares: Max. shares of referenced articles in Mashable \n\n30. self_reference_avg_sharess: Avg. shares of referenced articles in Mashable \n\n31. weekday_is_monday: Was the article published on a Monday? \n\n32. weekday_is_tuesday: Was the article published on a Tuesday? \n\n33. weekday_is_wednesday: Was the article published on a Wednesday? \n\n34. weekday_is_thursday: Was the article published on a Thursday? \n\n35. weekday_is_friday: Was the article published on a Friday? \n\n36. weekday_is_saturday: Was the article published on a Saturday? \n\n37. weekday_is_sunday: Was the article published on a Sunday? \n\n38. is_weekend: Was the article published on the weekend? \n\n39. LDA_00: Closeness to LDA topic 0 \n\n40. LDA_01: Closeness to LDA topic 1 \n\n41. LDA_02: Closeness to LDA topic 2 \n\n42. LDA_03: Closeness to LDA topic 3 \n\n43. LDA_04: Closeness to LDA topic 4 \n\n44. global_subjectivity: Text subjectivity \n\n45. global_sentiment_polarity: Text sentiment polarity \n\n46. global_rate_positive_words: Rate of positive words in the content \n\n47. global_rate_negative_words: Rate of negative words in the content \n\n48. rate_positive_words: Rate of positive words among non-neutral tokens \n\n49. rate_negative_words: Rate of negative words among non-neutral tokens \n\n50. avg_positive_polarity: Avg. polarity of positive words \n\n51. min_positive_polarity: Min. polarity of positive words \n\n52. max_positive_polarity: Max. polarity of positive words \n\n53. avg_negative_polarity: Avg. polarity of negative words \n\n54. min_negative_polarity: Min. polarity of negative words \n\n55. max_negative_polarity: Max. polarity of negative words \n\n56. title_subjectivity: Title subjectivity \n\n57. title_sentiment_polarity: Title polarity \n\n58. abs_title_subjectivity: Absolute subjectivity level \n\n59. abs_title_sentiment_polarity: Absolute polarity level \n\n60. shares: Number of shares (target)\n\n\n\n\n\nRelevant Papers:\n\n\n\nK. Fernandes, P. Vinagre and P. Cortez. A Proactive Intelligent Decision Support System for Predicting the Popularity of Online News. Proceedings of the 17th EPIA 2015 - Portuguese Conference on Artificial Intelligence, September, Coimbra, Portugal.\n\n\n\n\n\n\n\nCitation Request:\n\n\n\nK. Fernandes, P. Vinagre and P. Cortez. A Proactive Intelligent Decision Support System for Predicting the Popularity of Online News. Proceedings of the 17th EPIA 2015 - Portuguese Conference on Artificial Intelligence, September, Coimbra, Portugal.", "creator": null, "contributor": "Leo Grin", "collection_date": null, "upload_date": "2022-06-18T13:12:59", "language": null, "license": "Public", "default_target_attribute": "shares", "row_id_attribute": null, "ignore_attribute": null, "tags": null, "features": [{"index": 0, "name": "timedelta", "data_type": "numeric", "nominal_values": null, "number_missing_values": 0}, {"index": 1, "name": "n_tokens_title", "data_type": "numeric", "nominal_values": null, "number_missing_values": 0}, {"index": 2, "name": "n_tokens_content", "data_type": "numeric", "nominal_values": null, "number_missing_values": 0}, {"index": 3, "name": "n_unique_tokens", "data_type": "numeric", "nominal_values": null, "number_missing_values": 0}, {"index": 4, "name": "n_non_stop_words", "data_type": "numeric", "nominal_values": null, "number_missing_values": 0}, {"index": 5, "name": "n_non_stop_unique_tokens", "data_type": "numeric", "nominal_values": null, "number_missing_values": 0}, {"index": 6, "name": "num_hrefs", "data_type": "numeric", "nominal_values": null, "number_missing_values": 0}, {"index": 7, "name": "num_self_hrefs", "data_type": "numeric", "nominal_values": null, "number_missing_values": 0}, {"index": 8, "name": "num_imgs", "data_type": "numeric", "nominal_values": null, "number_missing_values": 0}, {"index": 9, "name": "num_videos", "data_type": "numeric", "nominal_values": null, "number_missing_values": 0}, {"index": 10, "name": "average_token_length", "data_type": "numeric", "nominal_values": null, "number_missing_values": 0}, {"index": 11, "name": "num_keywords", "data_type": "numeric", "nominal_values": null, "number_missing_values": 0}, {"index": 12, "name": "data_channel_is_lifestyle", "data_type": "nominal", "nominal_values": ["0", "1"], "number_missing_values": 0}, {"index": 13, "name": "data_channel_is_entertainment", "data_type": "nominal", "nominal_values": ["0", "1"], "number_missing_values": 0}, {"index": 14, "name": "data_channel_is_bus", "data_type": "nominal", "nominal_values": ["0", "1"], "number_missing_values": 0}, {"index": 15, "name": "data_channel_is_socmed", "data_type": "nominal", "nominal_values": ["0", "1"], "number_missing_values": 0}, {"index": 16, "name": "data_channel_is_tech", "data_type": "nominal", "nominal_values": ["0", "1"], "number_missing_values": 0}, {"index": 17, "name": "data_channel_is_world", "data_type": "nominal", "nominal_values": ["0", "1"], "number_missing_values": 0}, {"index": 18, "name": "kw_min_min", "data_type": "numeric", "nominal_values": null, "number_missing_values": 0}, {"index": 19, "name": "kw_max_min", "data_type": "numeric", "nominal_values": null, "number_missing_values": 0}, {"index": 20, "name": "kw_avg_min", "data_type": "numeric", "nominal_values": null, "number_missing_values": 0}, {"index": 21, "name": "kw_min_max", "data_type": "numeric", "nominal_values": null, "number_missing_values": 0}, {"index": 22, "name": "kw_max_max", "data_type": "numeric", "nominal_values": null, "number_missing_values": 0}, {"index": 23, "name": "kw_avg_max", "data_type": "numeric", "nominal_values": null, "number_missing_values": 0}, {"index": 24, "name": "kw_min_avg", "data_type": "numeric", "nominal_values": null, "number_missing_values": 0}, {"index": 25, "name": "kw_max_avg", "data_type": "numeric", "nominal_values": null, "number_missing_values": 0}, {"index": 26, "name": "kw_avg_avg", "data_type": "numeric", "nominal_values": null, "number_missing_values": 0}, {"index": 27, "name": "self_reference_min_shares", "data_type": "numeric", "nominal_values": null, "number_missing_values": 0}, {"index": 28, "name": "self_reference_max_shares", "data_type": "numeric", "nominal_values": null, "number_missing_values": 0}, {"index": 29, "name": "self_reference_avg_sharess", "data_type": "numeric", "nominal_values": null, "number_missing_values": 0}, {"index": 30, "name": "weekday_is_monday", "data_type": "nominal", "nominal_values": ["0", "1"], "number_missing_values": 0}, {"index": 31, "name": "weekday_is_tuesday", "data_type": "nominal", "nominal_values": ["0", "1"], "number_missing_values": 0}, {"index": 32, "name": "weekday_is_wednesday", "data_type": "nominal", "nominal_values": ["0", "1"], "number_missing_values": 0}, {"index": 33, "name": "weekday_is_thursday", "data_type": "nominal", "nominal_values": ["0", "1"], "number_missing_values": 0}, {"index": 34, "name": "weekday_is_friday", "data_type": "nominal", "nominal_values": ["0", "1"], "number_missing_values": 0}, {"index": 35, "name": "weekday_is_saturday", "data_type": "nominal", "nominal_values": ["0", "1"], "number_missing_values": 0}, {"index": 36, "name": "weekday_is_sunday", "data_type": "nominal", "nominal_values": ["0", "1"], "number_missing_values": 0}, {"index": 37, "name": "is_weekend", "data_type": "nominal", "nominal_values": ["0", "1"], "number_missing_values": 0}, {"index": 38, "name": "LDA_00", "data_type": "numeric", "nominal_values": null, "number_missing_values": 0}, {"index": 39, "name": "LDA_01", "data_type": "numeric", "nominal_values": null, "number_missing_values": 0}, {"index": 40, "name": "LDA_02", "data_type": "numeric", "nominal_values": null, "number_missing_values": 0}, {"index": 41, "name": "LDA_03", "data_type": "numeric", "nominal_values": null, "number_missing_values": 0}, {"index": 42, "name": "LDA_04", "data_type": "numeric", "nominal_values": null, "number_missing_values": 0}, {"index": 43, "name": "global_subjectivity", "data_type": "numeric", "nominal_values": null, "number_missing_values": 0}, {"index": 44, "name": "global_sentiment_polarity", "data_type": "numeric", "nominal_values": null, "number_missing_values": 0}, {"index": 45, "name": "global_rate_positive_words", "data_type": "numeric", "nominal_values": null, "number_missing_values": 0}, {"index": 46, "name": "global_rate_negative_words", "data_type": "numeric", "nominal_values": null, "number_missing_values": 0}, {"index": 47, "name": "rate_positive_words", "data_type": "numeric", "nominal_values": null, "number_missing_values": 0}, {"index": 48, "name": "rate_negative_words", "data_type": "numeric", "nominal_values": null, "number_missing_values": 0}, {"index": 49, "name": "avg_positive_polarity", "data_type": "numeric", "nominal_values": null, "number_missing_values": 0}, {"index": 50, "name": "min_positive_polarity", "data_type": "numeric", "nominal_values": null, "number_missing_values": 0}, {"index": 51, "name": "max_positive_polarity", "data_type": "numeric", "nominal_values": null, "number_missing_values": 0}, {"index": 52, "name": "avg_negative_polarity", "data_type": "numeric", "nominal_values": null, "number_missing_values": 0}, {"index": 53, "name": "min_negative_polarity", "data_type": "numeric", "nominal_values": null, "number_missing_values": 0}, {"index": 54, "name": "max_negative_polarity", "data_type": "numeric", "nominal_values": null, "number_missing_values": 0}, {"index": 55, "name": "title_subjectivity", "data_type": "numeric", "nominal_values": null, "number_missing_values": 0}, {"index": 56, "name": "title_sentiment_polarity", "data_type": "numeric", "nominal_values": null, "number_missing_values": 0}, {"index": 57, "name": "abs_title_subjectivity", "data_type": "numeric", "nominal_values": null, "number_missing_values": 0}, {"index": 58, "name": "abs_title_sentiment_polarity", "data_type": "numeric", "nominal_values": null, "number_missing_values": 0}, {"index": 59, "name": "shares", "data_type": "numeric", "nominal_values": null, "number_missing_values": 0}], "qualities": {"AutoCorrelation": 0.048687049895252785, "Dimensionality": 0.0015134698819493492, "MajorityClassPercentage": NaN, "MajorityClassSize": NaN, "MinorityClassPercentage": NaN, "MinorityClassSize": NaN, "NumberOfBinaryFeatures": 14.0, "NumberOfClasses": 0.0, "NumberOfFeatures": 60.0, "NumberOfInstances": 39644.0, "NumberOfInstancesWithMissingValues": 0.0, "NumberOfMissingValues": 0.0, "NumberOfNumericFeatures": 46.0, "NumberOfSymbolicFeatures": 14.0, "PercentageOfBinaryFeatures": 23.333333333333332, "PercentageOfInstancesWithMissingValues": 0.0, "PercentageOfMissingValues": 0.0, "PercentageOfNumericFeatures": 76.66666666666667, "PercentageOfSymbolicFeatures": 23.333333333333332}}